snf/R.py
snf/__init__.py
snf/_version.py
snf/compute.py
snf/cv.py
snf/datasets.py
snf/matlab.py
snf/metrics.py
snf/tests/__init__.py
snf/tests/conftest.py
snf/tests/test_compute.py
snf/tests/test_cv.py
snf/tests/test_metrics.py
snf/tests/data/digits/fourier.csv
snf/tests/data/digits/label.csv
snf/tests/data/digits/pixel.csv
snf/tests/data/digits/profile.csv
snf/tests/data/digits/zer.csv
snf/tests/data/sim/data1.csv
snf/tests/data/sim/data2.csv
snf/tests/data/sim/label.csv
snfpy-0.2.2.dist-info/COPYING.LESSER
snfpy-0.2.2.dist-info/LICENSE
snfpy-0.2.2.dist-info/METADATA
snfpy-0.2.2.dist-info/WHEEL
snfpy-0.2.2.dist-info/top_level.txt
snfpy-0.2.2.dist-info/RECORD
