Metadata-Version: 2.1
Name: snfpy
Version: 0.2.2
Summary: A Python toolbox for performing similarity network fusion (SNF)
Home-page: https://github.com/rmarkello/snfpy
Author: snfpy developers
Maintainer: Ross Markello
Maintainer-email: rossmarkello@gmail.com
License: LGPGv3
Download-URL: https://github.com/rmarkello/snfpy
Platform: OS Independent
Classifier: Development Status :: 3 - Alpha
Classifier: Intended Audience :: Science/Research
Classifier: License :: OSI Approved :: GNU Lesser General Public License v3 (LGPLv3)
Classifier: Programming Language :: Python :: 3.5
Classifier: Programming Language :: Python :: 3.6
Provides: snf
Requires-Python: >=3.5.1
Requires-Dist: numpy (>=1.14)
Requires-Dist: scikit-learn
Requires-Dist: scipy
Provides-Extra: all
Requires-Dist: sphinx (>=2.0) ; extra == 'all'
Requires-Dist: sphinx-rtd-theme ; extra == 'all'
Requires-Dist: flake8 ; extra == 'all'
Requires-Dist: pytest-cov ; extra == 'all'
Provides-Extra: doc
Requires-Dist: sphinx (>=2.0) ; extra == 'doc'
Requires-Dist: sphinx-rtd-theme ; extra == 'doc'
Provides-Extra: style
Requires-Dist: flake8 ; extra == 'style'
Provides-Extra: test
Requires-Dist: pytest-cov ; extra == 'test'
